django_sonic_screwdriver/__init__.py
django_sonic_screwdriver/admin.py
django_sonic_screwdriver/exceptions.py
django_sonic_screwdriver/models.py
django_sonic_screwdriver/settings.py
django_sonic_screwdriver/views.py
django_sonic_screwdriver/git/__init__.py
django_sonic_screwdriver/git/decorators.py
django_sonic_screwdriver/git/git.py
django_sonic_screwdriver/management/__init__.py
django_sonic_screwdriver/management/commands/__init__.py
django_sonic_screwdriver/management/commands/cache:clear.py
django_sonic_screwdriver/management/commands/gen:secretkey.py
django_sonic_screwdriver/management/commands/git:add.py
django_sonic_screwdriver/management/commands/git:branch.py
django_sonic_screwdriver/management/commands/git:tag.py
django_sonic_screwdriver/management/commands/git:tag:delete.py
django_sonic_screwdriver/management/commands/git:tag:push.py
django_sonic_screwdriver/management/commands/patch.py
django_sonic_screwdriver/management/commands/pypi:export.py
django_sonic_screwdriver/management/commands/pypi:upload.py
django_sonic_screwdriver/migrations/__init__.py
django_sonic_screwdriver/utils/__init__.py
django_sonic_screwdriver/utils/shell.py
django_sonic_screwdriver/version/__init__.py
django_sonic_screwdriver/version/tags.py
django_sonic_screwdriver/version/version.py
django_sonic_screwdriver-0.2.2.dist-info/DESCRIPTION.rst
django_sonic_screwdriver-0.2.2.dist-info/METADATA
django_sonic_screwdriver-0.2.2.dist-info/metadata.json
django_sonic_screwdriver-0.2.2.dist-info/RECORD
django_sonic_screwdriver-0.2.2.dist-info/top_level.txt
django_sonic_screwdriver-0.2.2.dist-info/WHEEL
sonic_screwdriver/__init__.py
sonic_screwdriver/settings.py
sonic_screwdriver/urls.py
sonic_screwdriver/wsgi.py
tests/__init__.py
tests/test.py
