Metadata-Version: 2.0
Name: django-sonic-screwdriver
Version: 0.2.2
Summary: Django Sonic Screwdriver is a collection of very useful commands and will make your life easier.
Home-page: https://github.com/rhazdon/django-sonic-screwdriver
Author: Djordje Ilic
Author-email: djordje.ilic@posteo.de
License: MIT License
Platform: UNKNOWN
Classifier: Development Status :: 3 - Alpha
Classifier: Environment :: Plugins
Classifier: Environment :: Web Environment
Classifier: Framework :: Django
Classifier: Framework :: Django :: 1.8
Classifier: Intended Audience :: Developers
Classifier: License :: OSI Approved :: MIT License
Classifier: Operating System :: OS Independent
Classifier: Programming Language :: Python
Classifier: Programming Language :: Python :: 3
Classifier: Programming Language :: Python :: 3.2
Classifier: Programming Language :: Python :: 3.3
Classifier: Programming Language :: Python :: 3.5
Classifier: Programming Language :: Python :: Implementation :: PyPy
Classifier: Topic :: Utilities
Requires-Dist: six (>=1.10)
Requires-Dist: wheel (>=0.26.0)
